LICENSE
MANIFEST.in
README.rst
setup.py
WebCronMon.egg-info/PKG-INFO
WebCronMon.egg-info/SOURCES.txt
WebCronMon.egg-info/dependency_links.txt
WebCronMon.egg-info/entry_points.txt
WebCronMon.egg-info/requires.txt
WebCronMon.egg-info/top_level.txt
webcronmon/__init__.py
webcronmon/api.py
webcronmon/config.ini.example
webcronmon/config.py
webcronmon/scripts.py
webcronmon/views.py
webcronmon.egg-info/SOURCES.txt
webcronmon/static/custom.css
webcronmon/static/hint.css
webcronmon/static/js/jquery.js
webcronmon/static/js/refresh.js
webcronmon/static/zurb/css/foundation.css
webcronmon/static/zurb/css/foundation.min.css
webcronmon/static/zurb/css/normalize.css
webcronmon/static/zurb/js/foundation.min.js
webcronmon/static/zurb/js/vendor/custom.modernizr.js
webcronmon/templates/index.html