Metadata-Version: 1.1
Name: webcronmon
Version: 1.0.2
Summary: Webcron.org Site Monitor
Home-page: https://pypi.python.org/pypi/webcronmon
Author: Seantis GmbH
Author-email: info@seantis.ch
License: MIT
Platform: any
Classifier: Development Status :: 4 - Beta
Classifier: Environment :: Web Environment
Classifier: Intended Audience :: Developers
Classifier: License :: OSI Approved :: MIT License
Classifier: Operating System :: OS Independent
Classifier: Programming Language :: Python
Classifier: Programming Language :: Python :: 2.7
Classifier: Topic :: Internet :: WWW/HTTP :: Dynamic Content
